brightpearlapi/BrightpearlAPI.py
brightpearlapi/__init__.py
brightpearlapi/models/__init__.py
brightpearlapi/models/common_classes.py
brightpearlapi/models/contact_classes_get.py
brightpearlapi/models/order_classes_get.py
brightpearlapi/models/order_classes_post.py
brightpearlapi/models/warehouse_classes_get.py
brightpearlapi/models/warehouse_classes_post.py
brightpearlapi/services/BaseClient.py
brightpearlapi/services/ContactClient.py
brightpearlapi/services/OrdersClient.py
brightpearlapi/services/ProductClient.py
brightpearlapi/services/WarehouseClient.py
brightpearlapi/services/__init__.py
brightpearlapi/utils/__init__.py
brightpearlapi/utils/connection.py
brightpearlapi/utils/exceptions.py
brightpearlapi/utils/search.py
brightpearlapi/utils/utils.py
brightpearlapi/utils/warehouse_enums.py
brightpearlapi-0.0.8.dist-info/LICENSE
brightpearlapi-0.0.8.dist-info/METADATA
brightpearlapi-0.0.8.dist-info/WHEEL
brightpearlapi-0.0.8.dist-info/top_level.txt
brightpearlapi-0.0.8.dist-info/RECORD
